make_api_request/__init__.py
make_api_request/api_error.py
make_api_request/auth.py
make_api_request/base_client.py
make_api_request/binary_response.py
make_api_request/py.typed
make_api_request/query.py
make_api_request/request.py
make_api_request/response.py
make_api_request/retry.py
make_api_request/type_utils.py
make_api_request/utils.py
make_api_request-0.2.0.dist-info/LICENSE
make_api_request-0.2.0.dist-info/METADATA
make_api_request-0.2.0.dist-info/WHEEL
make_api_request-0.2.0.dist-info/RECORD
