Metadata-Version: 2.1
Name: make-api-request
Version: 0.2.0
Summary: A modern Python HTTP client library with built-in authentication and response handling
License: MIT
Author: Sideko
Author-email: team@sideko.dev
Requires-Python: >=3.8,<4.0
Classifier: Development Status :: 4 - Beta
Classifier: Intended Audience :: Developers
Classifier: License :: OSI Approved :: MIT License
Classifier: Programming Language :: Python :: 3
Classifier: Programming Language :: Python :: 3.8
Classifier: Programming Language :: Python :: 3.9
Classifier: Programming Language :: Python :: 3.10
Classifier: Programming Language :: Python :: 3.11
Classifier: Programming Language :: Python :: 3.12
Classifier: Programming Language :: Python :: 3.13
Classifier: Topic :: Internet :: WWW/HTTP :: HTTP Servers
Classifier: Topic :: Software Development :: Libraries :: Python Modules
Requires-Dist: asyncio (>=4.0.0,<5.0.0)
Requires-Dist: httpx (>=0.26.0,<1)
Requires-Dist: jsonpointer (>=3.0.0,<4.0.0)
Requires-Dist: pydantic (>=2.5.0,<3.0.0)
Requires-Dist: typing_extensions (>=4.0.0,<5.0.0)
